{
	"format_version": "1.12.0",
	"minecraft:geometry": [
		{
			"description": {
				"identifier": "geometry.unknown",
				"texture_width": 109.22667,
				"texture_height": 109.22667,
				"visible_bounds_width": 4,
				"visible_bounds_height": 4.5,
				"visible_bounds_offset": [0, 1.75, 0]
			},
			"bones": [
				{
					"name": "bipedHead",
					"pivot": [0, 24, 0]
				},
				{
					"name": "armorHead",
					"parent": "bipedHead",
					"pivot": [0, 24, 0]
				},
				{
					"name": "Hat2",
					"parent": "armorHead",
					"pivot": [2.00678, 24.90328, -4.02743],
					"rotation": [0, 180, 0]
				},
				{
					"name": "Hat",
					"parent": "Hat2",
					"pivot": [7.575, 22, -3.75],
					"cubes": [
						{
							"origin": [8.875, 22.125, -7.25],
							"size": [6.2, 2.975, 4.5],
							"pivot": [7.575, 22, -3.75],
							"rotation": [22.5, 0, -57.5],
							"uv": {
								"north": {"uv": [6.85333, 8.92], "uv_size": [-6.85333, -3.74933]},
								"east": {"uv": [6.85333, 5.08], "uv_size": [-6.85333, -3.792]},
								"south": {"uv": [6.85333, 5.08], "uv_size": [-6.85333, -3.792]},
								"west": {"uv": [10.65067, 5.08], "uv_size": [-3.78134, -3.792]},
								"up": {"uv": [0, 5.128], "uv_size": [6.85333, 3.792]},
								"down": {"uv": [6.856, 5.128], "uv_size": [-6.84, 3.79733]}
							}
						},
						{
							"origin": [4.675, 32.55, -7.95],
							"size": [10.225, 1.575, 5.3],
							"pivot": [7.575, 35.75, -3.65],
							"rotation": [-22.5, 0, 57.5],
							"uv": {
								"north": {"uv": [6.81067, 8.92], "uv_size": [-6.81067, -3.792]},
								"east": {"uv": [6.85333, 2.99467], "uv_size": [-6.85333, 2.08533]},
								"south": {"uv": [0, 2.99467], "uv_size": [6.82133, 2.08533]},
								"west": {"uv": [10.62933, 5.08], "uv_size": [-3.80266, -3.792]},
								"up": {"uv": [0, 5.128], "uv_size": [6.85333, 3.792]},
								"down": {"uv": [0, 5.128], "uv_size": [6.85333, 3.792]}
							}
						},
						{
							"origin": [-7.525, 22.125, -7.25],
							"size": [6.2, 2.975, 4.5],
							"pivot": [-0.025, 22, -3.75],
							"rotation": [22.5, 0, 57.5],
							"uv": {
								"north": {"uv": [6.85333, 8.92], "uv_size": [-6.85333, -3.74933]},
								"east": {"uv": [6.72533, 5.02667], "uv_size": [-6.72533, -3.73867]},
								"south": {"uv": [6.85333, 5.08], "uv_size": [-6.85333, -3.792]},
								"west": {"uv": [10.65067, 5.08], "uv_size": [-3.78134, -3.792]},
								"up": {"uv": [0, 5.128], "uv_size": [6.85333, 3.792]},
								"down": {"uv": [6.856, 5.128], "uv_size": [-6.84, 3.79733]}
							}
						},
						{
							"origin": [-7.35, 32.55, -7.95],
							"size": [10.225, 1.575, 5.3],
							"pivot": [-0.025, 35.75, -3.65],
							"rotation": [-22.5, 0, -57.5],
							"uv": {
								"north": {"uv": [6.81067, 8.92], "uv_size": [-6.81067, -3.792]},
								"east": {"uv": [6.85333, 2.99467], "uv_size": [-6.85333, 2.08533]},
								"south": {"uv": [0, 2.99467], "uv_size": [6.82133, 2.08533]},
								"west": {"uv": [6.85333, 2.99467], "uv_size": [-6.85333, 2.08533]},
								"up": {"uv": [0, 5.128], "uv_size": [6.75733, 3.792]},
								"down": {"uv": [0, 5.128], "uv_size": [6.85333, 3.792]}
							}
						},
						{
							"origin": [1.175, 31.75, -8.575],
							"size": [5.325, 1.875, 4.7],
							"uv": {
								"north": {"uv": [6.81067, 8.92], "uv_size": [-6.81067, -3.792]},
								"east": {"uv": [6.81067, 8.92], "uv_size": [-6.81067, -3.792]},
								"south": {"uv": [6.81067, 8.92], "uv_size": [-6.81067, -3.792]},
								"west": {"uv": [6.81067, 8.92], "uv_size": [-6.81067, -3.792]},
								"up": {"uv": [0, 5.128], "uv_size": [6.81067, 3.792]},
								"down": {"uv": [0, 5.128], "uv_size": [6.81067, 3.792]}
							}
						},
						{
							"origin": [2.275, 33.6, -8.575],
							"size": [3.125, 2.375, 4.575],
							"uv": {
								"north": {"uv": [6.81067, 8.92], "uv_size": [-6.81067, -3.792]},
								"east": {"uv": [6.81067, 8.92], "uv_size": [-6.81067, -3.792]},
								"south": {"uv": [6.81067, 8.92], "uv_size": [-6.81067, -3.792]},
								"west": {"uv": [6.81067, 8.92], "uv_size": [-6.81067, -3.792]},
								"up": {"uv": [0, 5.128], "uv_size": [6.81067, 3.792]},
								"down": {"uv": [0, 5.128], "uv_size": [6.81067, 3.792]}
							}
						},
						{
							"origin": [2.875, 35.35, -11.95],
							"size": [1.925, 2.775, 6.6],
							"pivot": [3.8375, 36.7375, -7.2],
							"rotation": [-12.5, 0, 0],
							"uv": {
								"north": {"uv": [10.62933, 5.08], "uv_size": [-3.80266, -3.792]},
								"east": {"uv": [10.62933, 5.08], "uv_size": [-3.80266, -3.792]},
								"south": {"uv": [10.62933, 5.08], "uv_size": [-3.80266, -3.36533]},
								"west": {"uv": [10.62933, 5.08], "uv_size": [-3.80266, -3.792]},
								"up": {"uv": [6.82667, 1.288], "uv_size": [3.80266, 3.792]},
								"down": {"uv": [6.82667, 1.288], "uv_size": [3.80266, 3.792]}
							}
						},
						{
							"origin": [1.2, 30.85, -14.25],
							"size": [5.2, 5.2, 5.7],
							"pivot": [3.5375, 33.4375, -11.2],
							"rotation": [0, 0, 45],
							"uv": {
								"north": {"uv": [6.81067, 8.92], "uv_size": [-6.81067, -3.792]},
								"east": {"uv": [6.81067, 8.92], "uv_size": [-6.81067, -3.792]},
								"south": {"uv": [6.81067, 8.92], "uv_size": [-6.81067, -3.792]},
								"west": {"uv": [6.81067, 8.92], "uv_size": [-6.81067, -3.792]},
								"up": {"uv": [0, 5.128], "uv_size": [6.81067, 3.792]},
								"down": {"uv": [0, 5.128], "uv_size": [6.81067, 3.792]}
							}
						},
						{
							"origin": [-0.8, 23.15, -12.95],
							"size": [9.4, 2.7, 5.4],
							"uv": {
								"north": {"uv": [6.81067, 8.92], "uv_size": [-6.81067, -3.792]},
								"east": {"uv": [6.81067, 8.92], "uv_size": [-6.81067, -3.792]},
								"south": {"uv": [6.81067, 8.92], "uv_size": [-6.81067, -3.792]},
								"west": {"uv": [6.81067, 8.92], "uv_size": [-6.81067, -3.792]},
								"up": {"uv": [0, 5.128], "uv_size": [6.81067, 3.792]},
								"down": {"uv": [0, 5.128], "uv_size": [6.81067, 3.792]}
							}
						},
						{
							"origin": [6.8, 25.55, -13.65],
							"size": [3.4, 3.2, 5.7],
							"uv": {
								"north": {"uv": [6.81067, 8.92], "uv_size": [-6.81067, -3.792]},
								"east": {"uv": [6.81067, 8.92], "uv_size": [-6.81067, -3.792]},
								"south": {"uv": [6.81067, 8.92], "uv_size": [-6.81067, -3.792]},
								"west": {"uv": [6.81067, 8.92], "uv_size": [-6.81067, -3.792]},
								"up": {"uv": [0, 5.128], "uv_size": [6.81067, 3.792]},
								"down": {"uv": [0, 5.128], "uv_size": [6.81067, 3.792]}
							}
						},
						{
							"origin": [3.1, 30.825, -4.4],
							"size": [2, 2, 0.5],
							"pivot": [3.8375, 32.5125, -4.15],
							"rotation": [0, 0, 45],
							"uv": {
								"north": {"uv": [6.81067, 8.92], "uv_size": [2, 2]},
								"east": {"uv": [6.81067, 8.92], "uv_size": [0.5, 2]},
								"south": {"uv": [6.81067, 8.92], "uv_size": [2, 2]},
								"west": {"uv": [6.81067, 8.92], "uv_size": [0.5, 2]},
								"up": {"uv": [8.81067, 9.42], "uv_size": [-2, -0.5]},
								"down": {"uv": [8.81067, 9.42], "uv_size": [-2, -0.5]}
							}
						},
						{
							"origin": [-1.35, 27.35, -12.95],
							"size": [2.525, 11.375, 4.6],
							"pivot": [-0.3875, 31.9875, -12.05],
							"rotation": [-3.18458, -6.79382, 25.18908],
							"uv": {
								"north": {"uv": [6.81067, 8.92], "uv_size": [-6.81067, -3.792]},
								"east": {"uv": [4.67733, 8.92], "uv_size": [-4.67733, -3.792]},
								"south": {"uv": [6.81067, 8.92], "uv_size": [-6.81067, -3.792]},
								"west": {"uv": [6.81067, 8.92], "uv_size": [-6.81067, -3.792]},
								"up": {"uv": [0, 5.128], "uv_size": [6.81067, 3.792]},
								"down": {"uv": [0, 5.128], "uv_size": [6.81067, 3.792]}
							}
						},
						{
							"origin": [-2.65, 25.55, -13.65],
							"size": [3.4, 3.2, 5.7],
							"uv": {
								"north": {"uv": [6.81067, 8.92], "uv_size": [-6.81067, -3.792]},
								"east": {"uv": [6.81067, 8.92], "uv_size": [-6.81067, -3.792]},
								"south": {"uv": [6.81067, 8.92], "uv_size": [-6.81067, -3.792]},
								"west": {"uv": [6.81067, 8.92], "uv_size": [-6.81067, -3.792]},
								"up": {"uv": [0, 5.128], "uv_size": [6.81067, 3.792]},
								"down": {"uv": [0, 5.128], "uv_size": [6.81067, 3.792]}
							}
						},
						{
							"origin": [6.375, 27.35, -12.95],
							"size": [2.525, 11.375, 4.6],
							"pivot": [7.9375, 31.9875, -12.05],
							"rotation": [-3.18458, 6.79382, -25.18908],
							"uv": {
								"north": {"uv": [6.81067, 8.92], "uv_size": [-6.81067, -3.792]},
								"east": {"uv": [4.67733, 8.92], "uv_size": [-4.67733, -3.792]},
								"south": {"uv": [6.81067, 8.92], "uv_size": [-6.81067, -3.792]},
								"west": {"uv": [6.81067, 8.92], "uv_size": [-6.81067, -3.792]},
								"up": {"uv": [0, 5.128], "uv_size": [6.81067, 3.792]},
								"down": {"uv": [0, 5.128], "uv_size": [6.81067, 3.792]}
							}
						},
						{
							"origin": [-1.05, 25.85, -14.45],
							"size": [9.4, 7.2, 5.9],
							"uv": {
								"north": {"uv": [6.81067, 8.92], "uv_size": [-6.81067, -3.792]},
								"east": {"uv": [6.81067, 8.92], "uv_size": [-6.81067, -3.792]},
								"south": {"uv": [6.81067, 8.92], "uv_size": [-6.81067, -3.792]},
								"west": {"uv": [6.81067, 8.92], "uv_size": [-6.81067, -3.792]},
								"up": {"uv": [0, 5.128], "uv_size": [6.81067, 3.792]},
								"down": {"uv": [0, 5.128], "uv_size": [6.81067, 3.792]}
							}
						}
					]
				},
				{
					"name": "Deko",
					"parent": "Hat2",
					"pivot": [-2.82967, 25.70983, -4.8323]
				},
				{
					"name": "bone11",
					"parent": "Deko",
					"pivot": [-2.82967, 25.70983, -4.8323],
					"cubes": [
						{
							"origin": [-4.92967, 24.87233, -5.8323],
							"size": [4.9, 1.675, 2],
							"pivot": [-2.82967, 25.70983, -4.8323],
							"rotation": [160.1751, -10.86189, -150.09633],
							"uv": {
								"north": {"uv": [0, 12.696], "uv_size": [6.73467, -3.70667]},
								"east": {"uv": [13.05067, 8.98933], "uv_size": [-2, 1.675]},
								"south": {"uv": [6.73467, 8.98933], "uv_size": [-6.73467, 3.70667]},
								"west": {"uv": [8.99733, 8.98933], "uv_size": [-2, 1.675]},
								"up": {"uv": [0, 12.696], "uv_size": [6.73467, -3.70667]},
								"down": {"uv": [0, 12.696], "uv_size": [6.73467, -3.70667]}
							}
						},
						{
							"origin": [-4.57567, 23.8035, -5.99763],
							"size": [3.4, 0.875, 1],
							"pivot": [-0.27567, 24.241, -5.39763],
							"rotation": [26.16473, 40.94474, 43.86377],
							"uv": {
								"north": {"uv": [0.01066, 12.82933], "uv_size": [6.79334, 3.835]},
								"east": {"uv": [0.01066, 12.82933], "uv_size": [6.79334, 3.835]},
								"south": {"uv": [0.01066, 12.82933], "uv_size": [6.79334, 3.835]},
								"west": {"uv": [0.01066, 12.82933], "uv_size": [6.79334, 3.835]},
								"up": {"uv": [6.804, 16.66433], "uv_size": [-6.79334, -3.835]},
								"down": {"uv": [6.804, 16.66433], "uv_size": [-6.79334, -3.835]}
							}
						},
						{
							"origin": [-6.03234, 26.05155, -5.15542],
							"size": [1.8, 1.275, 1.4],
							"pivot": [-4.53234, 26.68905, -4.45542],
							"rotation": [21.56014, -5.20563, 37.1364],
							"uv": {
								"north": {"uv": [0.01066, 12.82933], "uv_size": [6.79334, 3.835]},
								"east": {"uv": [0.01066, 12.82933], "uv_size": [6.79334, 3.835]},
								"south": {"uv": [0.01066, 12.82933], "uv_size": [6.79334, 3.835]},
								"west": {"uv": [0.01066, 12.82933], "uv_size": [6.79334, 3.835]},
								"up": {"uv": [6.804, 16.66433], "uv_size": [-6.79334, -3.835]},
								"down": {"uv": [6.804, 16.66433], "uv_size": [-6.79334, -3.835]}
							}
						},
						{
							"origin": [-6.91104, 29.03084, -5.29797],
							"size": [1.8, 0.925, 1.05],
							"pivot": [-7.31104, 28.79334, -4.77297],
							"rotation": [18.66447, -12.14727, 56.12469],
							"uv": {
								"north": {"uv": [0.01066, 12.82933], "uv_size": [6.79334, 3.835]},
								"east": {"uv": [0.01066, 12.82933], "uv_size": [6.79334, 3.835]},
								"south": {"uv": [0.01066, 12.82933], "uv_size": [6.79334, 3.835]},
								"west": {"uv": [0.01066, 12.82933], "uv_size": [6.79334, 3.835]},
								"up": {"uv": [6.804, 16.66433], "uv_size": [-6.79334, -3.835]},
								"down": {"uv": [6.804, 16.66433], "uv_size": [-6.79334, -3.835]}
							}
						}
					]
				},
				{
					"name": "bone13",
					"parent": "Deko",
					"pivot": [-2.42967, 25.70983, -12.6323],
					"cubes": [
						{
							"origin": [-5.6736, 25.03836, -11.45179],
							"size": [4.9, 1.675, 2],
							"pivot": [-3.2236, 25.87586, -10.45179],
							"rotation": [-173.00021, 27.95867, -147.97171],
							"uv": {
								"north": {"uv": [0, 12.696], "uv_size": [6.73467, -3.70667]},
								"east": {"uv": [13.05067, 8.98933], "uv_size": [-2, 1.675]},
								"south": {"uv": [6.73467, 8.98933], "uv_size": [-6.73467, 3.70667]},
								"west": {"uv": [8.99733, 8.98933], "uv_size": [-2, 1.675]},
								"up": {"uv": [0, 12.696], "uv_size": [6.73467, -3.70667]},
								"down": {"uv": [0, 12.696], "uv_size": [6.73467, -3.70667]}
							}
						},
						{
							"origin": [-6.32967, 24.37233, -11.1323],
							"size": [2.1, 1.275, 1.6],
							"pivot": [-2.42967, 25.70983, -12.6323],
							"rotation": [-16.60871, -23.81248, 53.8092],
							"uv": {
								"north": {"uv": [0.01066, 12.82933], "uv_size": [6.79334, 3.835]},
								"east": {"uv": [0.01066, 12.82933], "uv_size": [6.79334, 3.835]},
								"south": {"uv": [0.01066, 12.82933], "uv_size": [6.79334, 3.835]},
								"west": {"uv": [0.01066, 12.82933], "uv_size": [6.79334, 3.835]},
								"up": {"uv": [6.804, 16.66433], "uv_size": [-6.79334, -3.835]},
								"down": {"uv": [6.804, 16.66433], "uv_size": [-6.79334, -3.835]}
							}
						},
						{
							"origin": [-8.58618, 27.0706, -12.52354],
							"size": [1.8, 0.95, 1.05],
							"pivot": [-5.88618, 27.3581, -12.17354],
							"rotation": [-22.92623, -17.84379, 71.43039],
							"uv": {
								"north": {"uv": [6.83733, 12.82933], "uv_size": [-6.83733, 3.77334]},
								"east": {"uv": [6.83733, 12.82933], "uv_size": [-6.83733, 3.77334]},
								"south": {"uv": [0.01066, 12.82933], "uv_size": [6.79334, 3.835]},
								"west": {"uv": [10.67733, 8.98933], "uv_size": [-4.27733, 3.77334]},
								"up": {"uv": [0, 16.60267], "uv_size": [6.83733, -3.77334]},
								"down": {"uv": [0, 16.60267], "uv_size": [6.83733, -3.77334]}
							}
						}
					]
				},
				{
					"name": "bone15",
					"parent": "Deko",
					"pivot": [9.97967, 25.70983, -12.6323],
					"cubes": [
						{
							"origin": [7.17967, 24.87233, -11.3323],
							"size": [4.9, 1.675, 2],
							"pivot": [9.97967, 25.70983, -12.6323],
							"rotation": [-6.99979, 27.95867, -32.02829],
							"uv": {
								"north": {"uv": [0, 12.696], "uv_size": [6.73467, -3.70667]},
								"east": {"uv": [13.05067, 8.98933], "uv_size": [-2, 1.675]},
								"south": {"uv": [6.73467, 8.98933], "uv_size": [-6.73467, 3.70667]},
								"west": {"uv": [8.99733, 8.98933], "uv_size": [-2, 1.675]},
								"up": {"uv": [0, 12.696], "uv_size": [6.73467, -3.70667]},
								"down": {"uv": [0, 12.696], "uv_size": [6.73467, -3.70667]}
							}
						},
						{
							"origin": [11.77967, 24.37233, -11.1323],
							"size": [2.1, 1.275, 1.6],
							"pivot": [9.97967, 25.70983, -12.6323],
							"rotation": [-16.60871, 23.81248, -53.8092],
							"uv": {
								"north": {"uv": [0.01066, 12.82933], "uv_size": [6.79334, 3.835]},
								"east": {"uv": [0.01066, 12.82933], "uv_size": [6.79334, 3.835]},
								"south": {"uv": [0.01066, 12.82933], "uv_size": [6.79334, 3.835]},
								"west": {"uv": [0.01066, 12.82933], "uv_size": [6.79334, 3.835]},
								"up": {"uv": [6.804, 16.66433], "uv_size": [-6.79334, -3.835]},
								"down": {"uv": [6.804, 16.66433], "uv_size": [-6.79334, -3.835]}
							}
						},
						{
							"origin": [14.33618, 27.0706, -12.52354],
							"size": [1.8, 0.95, 1.05],
							"pivot": [13.43618, 27.3581, -12.17354],
							"rotation": [-22.92623, 17.84379, -71.43039],
							"uv": {
								"north": {"uv": [0.01066, 12.82933], "uv_size": [6.79334, 3.835]},
								"east": {"uv": [0.01066, 12.82933], "uv_size": [6.79334, 3.835]},
								"south": {"uv": [0.01066, 12.82933], "uv_size": [6.79334, 3.835]},
								"west": {"uv": [0.01066, 12.82933], "uv_size": [6.79334, 3.835]},
								"up": {"uv": [6.804, 16.66433], "uv_size": [-6.79334, -3.835]},
								"down": {"uv": [6.804, 16.66433], "uv_size": [-6.79334, -3.835]}
							}
						}
					]
				},
				{
					"name": "bone16",
					"parent": "Deko",
					"pivot": [10.37967, 25.70983, -4.8323],
					"cubes": [
						{
							"origin": [7.57967, 24.87233, -5.8323],
							"size": [4.9, 1.675, 2],
							"pivot": [10.37967, 25.70983, -4.8323],
							"rotation": [19.8249, -10.86189, -29.90367],
							"uv": {
								"north": {"uv": [0, 8.98933], "uv_size": [6.83733, 3.77334]},
								"east": {"uv": [14.47467, 8.98933], "uv_size": [-3.424, 3.77334]},
								"south": {"uv": [6.83733, 8.98933], "uv_size": [-6.83733, 3.77334]},
								"west": {"uv": [10.42133, 8.98933], "uv_size": [-3.424, 3.77334]},
								"up": {"uv": [0, 12.76267], "uv_size": [6.83733, -3.77334]},
								"down": {"uv": [0, 12.76267], "uv_size": [6.83733, -3.77334]}
							}
						},
						{
							"origin": [8.72567, 23.8035, -5.99763],
							"size": [3.4, 0.875, 1],
							"pivot": [7.82567, 24.241, -5.39763],
							"rotation": [26.16473, -40.94474, -43.86377],
							"uv": {
								"north": {"uv": [0.01066, 12.82933], "uv_size": [6.79334, 3.835]},
								"east": {"uv": [0.01066, 12.82933], "uv_size": [6.79334, 3.835]},
								"south": {"uv": [0.01066, 12.82933], "uv_size": [6.79334, 3.835]},
								"west": {"uv": [0.01066, 12.82933], "uv_size": [6.79334, 3.835]},
								"up": {"uv": [6.804, 16.66433], "uv_size": [-6.79334, -3.835]},
								"down": {"uv": [6.804, 16.66433], "uv_size": [-6.79334, -3.835]}
							}
						},
						{
							"origin": [11.78234, 26.05155, -5.15542],
							"size": [1.8, 1.275, 1.4],
							"pivot": [12.08234, 26.68905, -4.45542],
							"rotation": [21.56014, 5.20563, -37.1364],
							"uv": {
								"north": {"uv": [0.01066, 12.82933], "uv_size": [6.79334, 3.835]},
								"east": {"uv": [0.01066, 12.82933], "uv_size": [6.79334, 3.835]},
								"south": {"uv": [0.01066, 12.82933], "uv_size": [6.79334, 3.835]},
								"west": {"uv": [0.01066, 12.82933], "uv_size": [6.79334, 3.835]},
								"up": {"uv": [6.804, 16.66433], "uv_size": [-6.79334, -3.835]},
								"down": {"uv": [6.804, 16.66433], "uv_size": [-6.79334, -3.835]}
							}
						},
						{
							"origin": [12.66104, 29.03084, -5.29797],
							"size": [1.8, 0.925, 1.05],
							"pivot": [14.86104, 28.79334, -4.77297],
							"rotation": [18.66447, 12.14727, -56.12469],
							"uv": {
								"north": {"uv": [0.01066, 12.82933], "uv_size": [6.79334, 3.835]},
								"east": {"uv": [0.01066, 12.82933], "uv_size": [6.79334, 3.835]},
								"south": {"uv": [0.01066, 12.82933], "uv_size": [6.79334, 3.835]},
								"west": {"uv": [0.01066, 12.82933], "uv_size": [6.79334, 3.835]},
								"up": {"uv": [6.804, 16.66433], "uv_size": [-6.79334, -3.835]},
								"down": {"uv": [6.804, 16.66433], "uv_size": [-6.79334, -3.835]}
							}
						}
					]
				},
				{
					"name": "bone12",
					"parent": "Deko",
					"pivot": [-6.08618, 28.4581, -12.37354],
					"cubes": [
						{
							"origin": [-14.95, 23.775, -18.55],
							"size": [37.7, 28.35, 0],
							"uv": {
								"north": {"uv": [15.36, 0.456], "uv_size": [20.49067, 11.02667]},
								"east": {"uv": [15.36, 0.456], "uv_size": [20.49067, 11.02667]},
								"south": {"uv": [15.36, 0.456], "uv_size": [20.49067, 11.02667]},
								"west": {"uv": [15.36, 0.456], "uv_size": [20.49067, 11.02667]},
								"up": {"uv": [35.85067, 11.48267], "uv_size": [-20.49067, -11.02667]},
								"down": {"uv": [35.85067, 11.48267], "uv_size": [-20.49067, -11.02667]}
							}
						}
					]
				},
				{
					"name": "bipedBody",
					"pivot": [0, 24, 0]
				},
				{
					"name": "armorBody",
					"parent": "bipedBody",
					"pivot": [0, 24, 0]
				},
				{
					"name": "2.1",
					"parent": "armorBody",
					"pivot": [0.31875, 21.525, -1.63125],
					"rotation": [0, 180, 0],
					"cubes": [
						{
							"origin": [-10.825, 18.05, -5.7],
							"size": [12.7, 8.55, 5.1],
							"pivot": [0.275, 22.5, -1.125],
							"rotation": [0, 0, -90],
							"uv": {
								"north": {"uv": [6.81067, 8.92], "uv_size": [-6.81067, -3.792]},
								"east": {"uv": [4.67733, 8.92], "uv_size": [-4.67733, -3.792]},
								"south": {"uv": [6.81067, 8.92], "uv_size": [-6.81067, -3.792]},
								"west": {"uv": [6.81067, 8.92], "uv_size": [-6.81067, -3.792]},
								"up": {"uv": [0, 5.128], "uv_size": [6.81067, 3.792]},
								"down": {"uv": [0, 5.128], "uv_size": [6.81067, 3.792]}
							}
						}
					]
				},
				{
					"name": "bone7",
					"parent": "2.1",
					"pivot": [0.275, 22.5, -1.125],
					"cubes": [
						{
							"origin": [0.875, 22.9, -1.575],
							"size": [2.4, 1, 1.625],
							"pivot": [0.275, 22.5, -1.125],
							"rotation": [0, 0, -142.5],
							"uv": {
								"north": {"uv": [6.81067, 8.92], "uv_size": [-6.81067, -3.792]},
								"east": {"uv": [6.85333, 2.99467], "uv_size": [-6.85333, 2.08533]},
								"south": {"uv": [0, 1.288], "uv_size": [6.82133, 3.792]},
								"west": {"uv": [6.85333, 2.99467], "uv_size": [-6.85333, 2.08533]},
								"up": {"uv": [0, 5.128], "uv_size": [6.75733, 3.792]},
								"down": {"uv": [0, 5.128], "uv_size": [6.85333, 3.792]}
							}
						},
						{
							"origin": [-2.325, 22.9, -1.575],
							"size": [2.4, 1, 1.625],
							"pivot": [0.675, 22.5, -1.125],
							"rotation": [0, 0, 142.5],
							"uv": {
								"north": {"uv": [6.81067, 8.92], "uv_size": [-6.81067, -3.792]},
								"east": {"uv": [6.85333, 2.99467], "uv_size": [-6.85333, 2.08533]},
								"south": {"uv": [0, 1.288], "uv_size": [6.82133, 3.792]},
								"west": {"uv": [6.85333, 2.99467], "uv_size": [-6.85333, 2.08533]},
								"up": {"uv": [0, 5.128], "uv_size": [6.75733, 3.792]},
								"down": {"uv": [0, 5.128], "uv_size": [6.85333, 3.792]}
							}
						},
						{
							"origin": [0.675, 23.1, -1.15],
							"size": [11.3, 0.7, 0.9],
							"pivot": [0.675, 22.5, -1.125],
							"rotation": [0, 0, 90],
							"uv": {
								"north": {"uv": [6.81067, 8.92], "uv_size": [-6.81067, -3.792]},
								"east": {"uv": [6.85333, 2.99467], "uv_size": [-6.85333, 2.08533]},
								"south": {"uv": [0, 1.288], "uv_size": [6.82133, 3.792]},
								"west": {"uv": [6.85333, 2.99467], "uv_size": [-6.85333, 2.08533]},
								"up": {"uv": [0, 5.128], "uv_size": [6.75733, 3.792]},
								"down": {"uv": [0, 5.128], "uv_size": [6.85333, 3.792]}
							}
						},
						{
							"origin": [-11.025, 23.1, -1.15],
							"size": [11.3, 0.7, 0.9],
							"pivot": [0.275, 22.5, -1.125],
							"rotation": [0, 0, -90],
							"uv": {
								"north": {"uv": [6.81067, 8.92], "uv_size": [-6.81067, -3.792]},
								"east": {"uv": [6.85333, 2.99467], "uv_size": [-6.85333, 2.08533]},
								"south": {"uv": [0, 1.288], "uv_size": [6.82133, 3.792]},
								"west": {"uv": [6.85333, 2.99467], "uv_size": [-6.85333, 2.08533]},
								"up": {"uv": [0, 5.128], "uv_size": [6.75733, 3.792]},
								"down": {"uv": [0, 5.128], "uv_size": [6.85333, 3.792]}
							}
						}
					]
				},
				{
					"name": "bone6",
					"parent": "2.1",
					"pivot": [0.275, 22.5, -1.125],
					"cubes": [
						{
							"origin": [-4.025, 17.2, -0.925],
							"size": [3, 5.7, 0.55],
							"pivot": [0.275, 22.5, -1.125],
							"rotation": [7.5, 0, 0],
							"uv": {
								"north": {"uv": [6.81067, 8.92], "uv_size": [-6.81067, -3.792]},
								"east": {"uv": [4.67733, 8.92], "uv_size": [-4.67733, -3.792]},
								"south": {"uv": [6.81067, 8.92], "uv_size": [-6.81067, -3.792]},
								"west": {"uv": [6.81067, 8.92], "uv_size": [-6.81067, -3.792]},
								"up": {"uv": [0, 5.128], "uv_size": [6.81067, 3.792]},
								"down": {"uv": [0, 5.128], "uv_size": [6.81067, 3.792]}
							}
						},
						{
							"origin": [-4.025, 7.14324, -0.18963],
							"size": [2.975, 10.2, 0.5],
							"uv": {
								"north": {"uv": [6.81067, 8.92], "uv_size": [-6.81067, -3.792]},
								"east": {"uv": [4.67733, 8.92], "uv_size": [-4.67733, -3.792]},
								"south": {"uv": [6.81067, 5.128], "uv_size": [-6.81067, 3.792]},
								"west": {"uv": [6.81067, 8.92], "uv_size": [-6.81067, -3.792]},
								"up": {"uv": [0, 5.128], "uv_size": [6.81067, 3.792]},
								"down": {"uv": [0, 5.128], "uv_size": [6.81067, 3.792]}
							}
						},
						{
							"origin": [-3.825, 4.94324, 0.11037],
							"size": [2.675, 2.4, 0],
							"uv": {
								"north": {"uv": [6.81067, 16.75467], "uv_size": [-6.81067, 4.56]},
								"east": {"uv": [6.81067, 16.75467], "uv_size": [-6.81067, 4.56]},
								"south": {"uv": [6.81067, 16.75467], "uv_size": [-6.81067, 4.56]},
								"west": {"uv": [6.81067, 16.75467], "uv_size": [-6.81067, 4.56]},
								"up": {"uv": [0, 21.31467], "uv_size": [6.81067, -4.56]},
								"down": {"uv": [0, 21.31467], "uv_size": [6.81067, -4.56]}
							}
						},
						{
							"origin": [-4.525, 22, -6.175],
							"size": [2.2, 3.525, 6.6],
							"uv": {
								"north": {"uv": [6.81067, 8.92], "uv_size": [-6.81067, -3.792]},
								"east": {"uv": [6.81067, 8.92], "uv_size": [-6.81067, -3.792]},
								"south": {"uv": [6.81067, 8.92], "uv_size": [-6.81067, -3.792]},
								"west": {"uv": [6.81067, 8.92], "uv_size": [-6.81067, -3.792]},
								"up": {"uv": [0, 5.128], "uv_size": [6.81067, 3.792]},
								"down": {"uv": [0, 5.128], "uv_size": [6.81067, 3.792]}
							}
						},
						{
							"origin": [1.975, 17.2, -0.925],
							"size": [3, 5.7, 0.55],
							"pivot": [0.675, 22.5, -1.125],
							"rotation": [7.5, 0, 0],
							"uv": {
								"north": {"uv": [6.81067, 8.92], "uv_size": [-6.81067, -3.792]},
								"east": {"uv": [4.67733, 8.92], "uv_size": [-4.67733, -3.792]},
								"south": {"uv": [6.81067, 8.92], "uv_size": [-6.81067, -3.792]},
								"west": {"uv": [6.81067, 8.92], "uv_size": [-6.81067, -3.792]},
								"up": {"uv": [0, 5.128], "uv_size": [6.81067, 3.792]},
								"down": {"uv": [0, 5.128], "uv_size": [6.81067, 3.792]}
							}
						},
						{
							"origin": [2, 7.14324, -0.18963],
							"size": [2.975, 10.2, 0.5],
							"uv": {
								"north": {"uv": [6.81067, 8.92], "uv_size": [-6.81067, -3.792]},
								"east": {"uv": [4.67733, 8.92], "uv_size": [-4.67733, -3.792]},
								"south": {"uv": [6.81067, 5.128], "uv_size": [-6.81067, 3.792]},
								"west": {"uv": [6.81067, 8.92], "uv_size": [-6.81067, -3.792]},
								"up": {"uv": [0, 5.128], "uv_size": [6.81067, 3.792]},
								"down": {"uv": [0, 5.128], "uv_size": [6.81067, 3.792]}
							}
						},
						{
							"origin": [2.1, 4.94324, 0.11037],
							"size": [2.675, 2.4, 0],
							"uv": {
								"north": {"uv": [6.81067, 16.75467], "uv_size": [-6.81067, 4.56]},
								"east": {"uv": [6.81067, 16.75467], "uv_size": [-6.81067, 4.56]},
								"south": {"uv": [6.81067, 16.75467], "uv_size": [-6.81067, 4.56]},
								"west": {"uv": [6.81067, 16.75467], "uv_size": [-6.81067, 4.56]},
								"up": {"uv": [0, 21.31467], "uv_size": [6.81067, -4.56]},
								"down": {"uv": [0, 21.31467], "uv_size": [6.81067, -4.56]}
							}
						},
						{
							"origin": [5.475, 22, -5.875],
							"size": [0.2, 1.725, 6],
							"uv": {
								"north": {"uv": [6.81067, 8.92], "uv_size": [-6.81067, -3.792]},
								"east": {"uv": [6.81067, 8.92], "uv_size": [-6.81067, -3.792]},
								"south": {"uv": [6.81067, 8.92], "uv_size": [-6.81067, -3.792]},
								"west": {"uv": [6.81067, 8.92], "uv_size": [-6.81067, -3.792]},
								"up": {"uv": [0, 5.128], "uv_size": [6.81067, 3.792]},
								"down": {"uv": [0, 5.128], "uv_size": [6.81067, 3.792]}
							}
						},
						{
							"origin": [-3.5, 4.94324, -6.66037],
							"size": [8.575, 4.4, 0],
							"uv": {
								"north": {"uv": [6.81067, 16.75467], "uv_size": [-6.81067, 4.56]},
								"east": {"uv": [6.81067, 16.75467], "uv_size": [-6.81067, 4.56]},
								"south": {"uv": [6.81067, 16.75467], "uv_size": [-6.81067, 4.56]},
								"west": {"uv": [6.81067, 16.75467], "uv_size": [-6.81067, 4.56]},
								"up": {"uv": [0, 21.31467], "uv_size": [6.81067, -4.56]},
								"down": {"uv": [0, 21.31467], "uv_size": [6.81067, -4.56]}
							}
						},
						{
							"origin": [-3.625, 17.2, -6.075],
							"size": [8.8, 6.9, 0.55],
							"pivot": [0.675, 22.5, -5.325],
							"rotation": [-7.5, 0, 0],
							"uv": {
								"north": {"uv": [0, 8.92], "uv_size": [6.81067, -3.792]},
								"east": {"uv": [4.67733, 8.92], "uv_size": [-4.67733, -3.792]},
								"south": {"uv": [0, 5.128], "uv_size": [6.81067, 3.792]},
								"west": {"uv": [6.81067, 8.92], "uv_size": [-6.81067, -3.792]},
								"up": {"uv": [0, 5.128], "uv_size": [6.81067, 3.792]},
								"down": {"uv": [0, 5.128], "uv_size": [6.81067, 3.792]}
							}
						},
						{
							"origin": [-3.6, 9.14324, -6.76037],
							"size": [8.775, 8.2, 0.5],
							"uv": {
								"north": {"uv": [6.81067, 8.92], "uv_size": [-6.81067, -3.792]},
								"east": {"uv": [4.67733, 8.92], "uv_size": [-4.67733, -3.792]},
								"south": {"uv": [6.81067, 5.128], "uv_size": [-6.81067, 3.792]},
								"west": {"uv": [6.81067, 8.92], "uv_size": [-6.81067, -3.792]},
								"up": {"uv": [0, 5.128], "uv_size": [6.81067, 3.792]},
								"down": {"uv": [0, 5.128], "uv_size": [6.81067, 3.792]}
							}
						},
						{
							"origin": [-2.225, 14.51824, -7.86037],
							"size": [6.025, 5.45, 0],
							"pivot": [3.35, 17.24324, -8.03537],
							"rotation": [-4, 0, 0],
							"uv": {
								"north": {"uv": [36.14667, 0.81333], "uv_size": [9.54133, 9.90667]},
								"east": {"uv": [45.688, 0.81333], "uv_size": [-9.54133, 9.90667]},
								"south": {"uv": [45.688, 0.81333], "uv_size": [-9.54133, 9.90667]},
								"west": {"uv": [45.688, 0.81333], "uv_size": [-9.54133, 9.90667]},
								"up": {"uv": [36.14667, 10.72], "uv_size": [9.54133, -9.90667]},
								"down": {"uv": [36.14667, 10.72], "uv_size": [9.54133, -9.90667]}
							}
						},
						{
							"origin": [-4.725, 22, -5.875],
							"size": [0.2, 1.725, 6],
							"uv": {
								"north": {"uv": [6.81067, 8.92], "uv_size": [-6.81067, -3.792]},
								"east": {"uv": [6.81067, 8.92], "uv_size": [-6.81067, -3.792]},
								"south": {"uv": [6.81067, 8.92], "uv_size": [-6.81067, -3.792]},
								"west": {"uv": [6.81067, 8.92], "uv_size": [-6.81067, -3.792]},
								"up": {"uv": [0, 5.128], "uv_size": [6.81067, 3.792]},
								"down": {"uv": [0, 5.128], "uv_size": [6.81067, 3.792]}
							}
						},
						{
							"origin": [3.275, 22, -6.175],
							"size": [2.2, 3.525, 6.6],
							"uv": {
								"north": {"uv": [6.81067, 8.92], "uv_size": [-6.81067, -3.792]},
								"east": {"uv": [6.81067, 8.92], "uv_size": [-6.81067, -3.792]},
								"south": {"uv": [6.81067, 8.92], "uv_size": [-6.81067, -3.792]},
								"west": {"uv": [6.81067, 8.92], "uv_size": [-6.81067, -3.792]},
								"up": {"uv": [0, 5.128], "uv_size": [6.81067, 3.792]},
								"down": {"uv": [0, 5.128], "uv_size": [6.81067, 3.792]}
							}
						}
					]
				},
				{
					"name": "bone8",
					"parent": "2.1",
					"pivot": [0.275, 23.4, -1.125],
					"cubes": [
						{
							"origin": [-10.925, 18.6, -5.95],
							"size": [1.4, 9.2, 5.6],
							"pivot": [0.275, 23.4, -1.125],
							"rotation": [0, 0, -90],
							"uv": {
								"north": {"uv": [2.544, 25.13333], "uv_size": [-2.544, -3.792]},
								"east": {"uv": [4.67733, 25.13333], "uv_size": [-4.67733, -3.792]},
								"south": {"uv": [2.544, 25.13333], "uv_size": [-2.544, -3.792]},
								"west": {"uv": [6.81067, 25.13333], "uv_size": [-6.81067, -3.792]},
								"up": {"uv": [0, 21.34133], "uv_size": [2.544, 3.792]},
								"down": {"uv": [0, 21.34133], "uv_size": [2.544, 3.792]}
							}
						},
						{
							"origin": [10.65, 22.775, -0.45],
							"size": [0.85, 1.05, 0.3],
							"pivot": [0.575, 23.4, -1.125],
							"rotation": [0, 0, 90],
							"uv": {
								"north": {"uv": [10.66667, 16.60267], "uv_size": [3.85066, -3.77334]},
								"east": {"uv": [10.66667, 16.60267], "uv_size": [3.85066, -3.77334]},
								"south": {"uv": [10.66667, 16.60267], "uv_size": [3.85066, -3.77334]},
								"west": {"uv": [10.66667, 16.60267], "uv_size": [3.85066, -3.77334]},
								"up": {"uv": [14.51733, 12.82933], "uv_size": [-3.85066, 3.77334]},
								"down": {"uv": [14.51733, 12.82933], "uv_size": [-3.85066, 3.77334]}
							}
						},
						{
							"origin": [10.525, 22.6, -0.45],
							"size": [1.1, 1.4, 0.2],
							"pivot": [0.575, 23.4, -1.125],
							"rotation": [0, 0, 90],
							"uv": {
								"north": {"uv": [6.81067, 25.13333], "uv_size": [-6.81067, -3.792]},
								"east": {"uv": [4.67733, 25.13333], "uv_size": [-4.67733, -3.792]},
								"south": {"uv": [6.81067, 25.13333], "uv_size": [-6.81067, -3.792]},
								"west": {"uv": [6.81067, 25.13333], "uv_size": [-6.81067, -3.792]},
								"up": {"uv": [0, 21.34133], "uv_size": [6.81067, 3.792]},
								"down": {"uv": [0, 21.34133], "uv_size": [6.81067, 3.792]}
							}
						}
					]
				},
				{
					"name": "bipedRightArm",
					"pivot": [-5, 22, 0]
				},
				{
					"name": "armorRightArm",
					"parent": "bipedRightArm",
					"pivot": [-5, 22, 0]
				},
				{
					"name": "2.2",
					"parent": "armorRightArm",
					"pivot": [-3.8, 22, 4.25],
					"cubes": [
						{
							"origin": [-8.4, 13.45, -2.55],
							"size": [4.5, 8.575, 5.1],
							"uv": {
								"north": {"uv": [6.81067, 8.92], "uv_size": [-6.81067, -3.792]},
								"east": {"uv": [10.70933, 23.42667], "uv_size": [3.78134, -6.608]},
								"south": {"uv": [14.49067, 23.42667], "uv_size": [-3.78134, -6.608]},
								"west": {"uv": [6.81067, 8.92], "uv_size": [-6.81067, -3.792]},
								"up": {"uv": [0, 5.128], "uv_size": [6.81067, 3.792]},
								"down": {"uv": [0, 5.128], "uv_size": [6.81067, 3.792]}
							}
						},
						{
							"origin": [-8.6, 22, -2.65],
							"size": [3.9, 2.425, 5.5],
							"uv": {
								"north": {"uv": [6.81067, 8.92], "uv_size": [-6.81067, -3.792]},
								"east": {"uv": [4.67733, 8.92], "uv_size": [-4.67733, -3.792]},
								"south": {"uv": [6.81067, 8.92], "uv_size": [-6.81067, -3.792]},
								"west": {"uv": [6.81067, 8.92], "uv_size": [-6.81067, -3.792]},
								"up": {"uv": [0, 5.128], "uv_size": [6.81067, 3.792]},
								"down": {"uv": [0, 5.128], "uv_size": [6.81067, 3.792]}
							}
						},
						{
							"origin": [-10.1, 19.475, -1.825],
							"size": [0.2, 3.625, 3.65],
							"pivot": [-3.8, 22, 4.25],
							"rotation": [0, 0, 35],
							"uv": {
								"north": {"uv": [36.144, 0.89867], "uv_size": [9.74133, 9.86933]},
								"east": {"uv": [36.144, 0.89867], "uv_size": [9.74133, 9.86933]},
								"south": {"uv": [36.144, 0.89867], "uv_size": [9.74133, 9.86933]},
								"west": {"uv": [36.144, 0.89867], "uv_size": [9.74133, 9.86933]},
								"up": {"uv": [45.88533, 10.768], "uv_size": [-9.74133, -9.86933]},
								"down": {"uv": [45.88533, 10.768], "uv_size": [-9.74133, -9.86933]}
							}
						},
						{
							"origin": [-8, 24.425, -2.15],
							"size": [3.3, 0.3, 4.5],
							"uv": {
								"north": {"uv": [6.81067, 8.92], "uv_size": [-6.81067, -3.792]},
								"east": {"uv": [4.67733, 8.92], "uv_size": [-4.67733, -3.792]},
								"south": {"uv": [6.81067, 8.92], "uv_size": [-6.81067, -3.792]},
								"west": {"uv": [6.81067, 8.92], "uv_size": [-6.81067, -3.792]},
								"up": {"uv": [0, 5.128], "uv_size": [6.81067, 3.792]},
								"down": {"uv": [0, 5.128], "uv_size": [6.81067, 3.792]}
							}
						}
					]
				},
				{
					"name": "bipedLeftArm",
					"pivot": [5, 22, 0]
				},
				{
					"name": "armorLeftArm",
					"parent": "bipedLeftArm",
					"pivot": [5, 22, 0]
				},
				{
					"name": "2.3",
					"parent": "armorLeftArm",
					"pivot": [3.8, 22, 4.25],
					"cubes": [
						{
							"origin": [3.9, 13.45, -2.55],
							"size": [4.5, 8.575, 5.1],
							"uv": {
								"north": {"uv": [0, 8.92], "uv_size": [6.81067, -3.792]},
								"east": {"uv": [0, 8.92], "uv_size": [6.81067, -3.792]},
								"south": {"uv": [10.70933, 23.42667], "uv_size": [3.78134, -6.608]},
								"west": {"uv": [14.49067, 23.42667], "uv_size": [-3.78134, -6.608]},
								"up": {"uv": [6.81067, 5.128], "uv_size": [-6.81067, 3.792]},
								"down": {"uv": [6.81067, 5.128], "uv_size": [-6.81067, 3.792]}
							}
						},
						{
							"origin": [4.8, 22, -2.65],
							"size": [3.8, 2.425, 5.5],
							"uv": {
								"north": {"uv": [6.81067, 8.92], "uv_size": [-6.81067, -3.792]},
								"east": {"uv": [4.67733, 8.92], "uv_size": [-4.67733, -3.792]},
								"south": {"uv": [6.81067, 8.92], "uv_size": [-6.81067, -3.792]},
								"west": {"uv": [6.81067, 8.92], "uv_size": [-6.81067, -3.792]},
								"up": {"uv": [0, 5.128], "uv_size": [6.81067, 3.792]},
								"down": {"uv": [0, 5.128], "uv_size": [6.81067, 3.792]}
							}
						},
						{
							"origin": [9.9, 19.475, -1.825],
							"size": [0.2, 3.625, 3.65],
							"pivot": [3.8, 22, 4.25],
							"rotation": [0, 0, -35],
							"uv": {
								"north": {"uv": [36.14667, 0.81333], "uv_size": [0.2, 3.625]},
								"east": {"uv": [49.338, 0.81333], "uv_size": [3.65, 3.625]},
								"south": {"uv": [45.688, 0.81333], "uv_size": [0.2, 3.625]},
								"west": {"uv": [36.144, 0.89867], "uv_size": [3.65, 3.625]},
								"up": {"uv": [45.888, 4.46333], "uv_size": [-0.2, -3.65]},
								"down": {"uv": [45.888, 4.46333], "uv_size": [-0.2, -3.65]}
							}
						},
						{
							"origin": [4.8, 24.425, -2.15],
							"size": [3.2, 0.3, 4.5],
							"uv": {
								"north": {"uv": [6.81067, 8.92], "uv_size": [-6.81067, -3.792]},
								"east": {"uv": [4.67733, 8.92], "uv_size": [-4.67733, -3.792]},
								"south": {"uv": [6.81067, 8.92], "uv_size": [-6.81067, -3.792]},
								"west": {"uv": [6.81067, 8.92], "uv_size": [-6.81067, -3.792]},
								"up": {"uv": [0, 5.128], "uv_size": [6.81067, 3.792]},
								"down": {"uv": [0, 5.128], "uv_size": [6.81067, 3.792]}
							}
						}
					]
				},
				{
					"name": "bipedLeftLeg",
					"pivot": [2, 12, 0]
				},
				{
					"name": "armorLeftLeg",
					"parent": "bipedLeftLeg",
					"pivot": [2, 12, 0],
					"cubes": [
						{
							"origin": [-4.8, 3.05, -3],
							"size": [5.35, 9.2, 6.3],
							"pivot": [0, 7.65, 0.11875],
							"rotation": [-180, 0, 180],
							"uv": {
								"north": {"uv": [6.81067, 25.13333], "uv_size": [-6.81067, -3.792]},
								"east": {"uv": [6.81067, 25.13333], "uv_size": [-6.81067, -3.792]},
								"south": {"uv": [6.81067, 25.13333], "uv_size": [-6.81067, -3.792]},
								"west": {"uv": [6.81067, 25.13333], "uv_size": [-6.81067, -3.792]},
								"up": {"uv": [0, 21.34133], "uv_size": [2.544, 3.792]},
								"down": {"uv": [0, 21.34133], "uv_size": [2.544, 3.792]}
							}
						}
					]
				},
				{
					"name": "armorLeftBoot",
					"parent": "bipedLeftLeg",
					"pivot": [2, 12, 0]
				},
				{
					"name": "4.1",
					"parent": "armorLeftBoot",
					"pivot": [1.78125, 1.29625, -0.01187],
					"cubes": [
						{
							"origin": [-0.2275, 1.035, -2.23375],
							"size": [4.3175, 0.5225, 4.44375],
							"pivot": [1.78125, 1.29625, -0.01187],
							"rotation": [0, 0, 5],
							"uv": {
								"north": {"uv": [2.544, 25.13333], "uv_size": [4.3175, 0.5225]},
								"east": {"uv": [4.67733, 25.13333], "uv_size": [4.44375, 0.5225]},
								"south": {"uv": [6.384, 23.42667], "uv_size": [4.3175, 0.5225]},
								"west": {"uv": [6.81067, 25.13333], "uv_size": [4.44375, 0.5225]},
								"up": {"uv": [6.8615, 29.57708], "uv_size": [-4.3175, -4.44375]},
								"down": {"uv": [6.8615, 29.57708], "uv_size": [-4.3175, -4.44375]}
							}
						},
						{
							"origin": [-0.2275, 2.09, -2.32875],
							"size": [4.3175, 0.5225, 4.63375],
							"pivot": [1.78125, 2.35125, -0.01187],
							"rotation": [0, 0, -10],
							"uv": {
								"north": {"uv": [2.544, 25.13333], "uv_size": [4.3175, 0.5225]},
								"east": {"uv": [4.67733, 25.13333], "uv_size": [4.63375, 0.5225]},
								"south": {"uv": [6.384, 23.42667], "uv_size": [4.3175, 0.5225]},
								"west": {"uv": [6.81067, 25.13333], "uv_size": [4.63375, 0.5225]},
								"up": {"uv": [6.8615, 29.76708], "uv_size": [-4.3175, -4.63375]},
								"down": {"uv": [6.8615, 29.76708], "uv_size": [-4.3175, -4.63375]}
							}
						},
						{
							"origin": [-0.2275, 2.185, -2.20875],
							"size": [4.3175, 0.5225, 4.39375],
							"pivot": [1.78125, 2.44625, -0.01187],
							"rotation": [0, 0, 5],
							"uv": {
								"north": {"uv": [2.544, 25.13333], "uv_size": [-2.544, -3.792]},
								"east": {"uv": [4.67733, 25.13333], "uv_size": [-4.67733, -3.792]},
								"south": {"uv": [6.384, 23.42667], "uv_size": [-6.384, -2.08534]},
								"west": {"uv": [6.81067, 25.13333], "uv_size": [-6.81067, -3.792]},
								"up": {"uv": [0, 21.34133], "uv_size": [2.544, 3.792]},
								"down": {"uv": [0, 21.34133], "uv_size": [2.544, 3.792]}
							}
						},
						{
							"origin": [-0.2275, 2.09, -2.30375],
							"size": [4.3175, 0.5225, 4.58375],
							"pivot": [1.78125, 2.35125, -0.01187],
							"rotation": [0, 0, -10],
							"uv": {
								"north": {"uv": [12, 6], "uv_size": [-4, 0]},
								"east": {"uv": [16, 6], "uv_size": [-4, 0]},
								"south": {"uv": [20, 6], "uv_size": [-4, 0]},
								"west": {"uv": [8, 6], "uv_size": [-4, 0]},
								"up": {"uv": [12, 2], "uv_size": [-4, 4]},
								"down": {"uv": [16, 6], "uv_size": [-4, -4]}
							}
						},
						{
							"origin": [-0.2275, 1.14, -2.30375],
							"size": [4.3175, 0.5225, 4.58375],
							"pivot": [1.78125, 1.40125, -0.01187],
							"rotation": [0, 0, -10],
							"uv": {
								"north": {"uv": [2.544, 25.13333], "uv_size": [-2.544, -3.792]},
								"east": {"uv": [4.67733, 25.13333], "uv_size": [-4.67733, -3.792]},
								"south": {"uv": [6.384, 23.42667], "uv_size": [-6.384, -2.08534]},
								"west": {"uv": [6.81067, 25.13333], "uv_size": [-6.81067, -3.792]},
								"up": {"uv": [0, 21.34133], "uv_size": [2.544, 3.792]},
								"down": {"uv": [0, 21.34133], "uv_size": [2.544, 3.792]}
							}
						},
						{
							"origin": [-0.1275, 0.285, -2.30875],
							"size": [4.2175, 0.5225, 4.59375],
							"pivot": [1.78125, 0.54625, -0.01187],
							"rotation": [0, 0, 5],
							"uv": {
								"north": {"uv": [2.544, 25.13333], "uv_size": [-2.544, -3.792]},
								"east": {"uv": [4.67733, 25.13333], "uv_size": [-4.67733, -3.792]},
								"south": {"uv": [6.384, 23.42667], "uv_size": [-6.384, -2.08534]},
								"west": {"uv": [6.81067, 25.13333], "uv_size": [-6.81067, -3.792]},
								"up": {"uv": [0, 21.34133], "uv_size": [2.544, 3.792]},
								"down": {"uv": [0, 21.34133], "uv_size": [2.544, 3.792]}
							}
						}
					]
				},
				{
					"name": "bipedRightLeg",
					"pivot": [-2, 12, 0]
				},
				{
					"name": "armorRightLeg",
					"parent": "bipedRightLeg",
					"pivot": [-2, 12, 0],
					"cubes": [
						{
							"origin": [-0.55, 3.05, -2.925],
							"size": [5.35, 9.2, 6.025],
							"pivot": [0, 7.65, 0.11875],
							"rotation": [-180, 0, 180],
							"uv": {
								"north": {"uv": [6.81067, 25.13333], "uv_size": [-6.81067, -3.792]},
								"east": {"uv": [6.81067, 25.13333], "uv_size": [-6.81067, -3.792]},
								"south": {"uv": [6.81067, 25.13333], "uv_size": [-6.81067, -3.792]},
								"west": {"uv": [6.81067, 25.13333], "uv_size": [-6.81067, -3.792]},
								"up": {"uv": [0, 21.34133], "uv_size": [2.544, 3.792]},
								"down": {"uv": [0, 21.34133], "uv_size": [2.544, 3.792]}
							}
						}
					]
				},
				{
					"name": "armorRightBoot",
					"parent": "bipedRightLeg",
					"pivot": [-2, 12, 0]
				},
				{
					"name": "4.2",
					"parent": "armorRightBoot",
					"pivot": [-1.78125, 2.64625, -0.01187],
					"cubes": [
						{
							"origin": [-4.09, 2.385, -2.30875],
							"size": [4.3175, 0.5225, 4.59375],
							"pivot": [-1.78125, 2.64625, -0.01187],
							"rotation": [0, 0, -5],
							"uv": {
								"north": {"uv": [2.544, 25.13333], "uv_size": [-2.544, -3.792]},
								"east": {"uv": [4.67733, 25.13333], "uv_size": [-4.67733, -3.792]},
								"south": {"uv": [6.384, 23.42667], "uv_size": [-6.384, -2.08534]},
								"west": {"uv": [6.81067, 25.13333], "uv_size": [-6.81067, -3.792]},
								"up": {"uv": [0, 21.34133], "uv_size": [2.544, 3.792]},
								"down": {"uv": [0, 21.34133], "uv_size": [2.544, 3.792]}
							}
						},
						{
							"origin": [-4.09, 2.19, -2.30375],
							"size": [4.3175, 0.5225, 4.58375],
							"pivot": [-1.78125, 2.45125, -0.01187],
							"rotation": [0, 0, 10],
							"uv": {
								"north": {"uv": [6.384, 23.42667], "uv_size": [-6.384, -2.08534]},
								"east": {"uv": [6.384, 23.42667], "uv_size": [-6.384, -2.08534]},
								"south": {"uv": [6.384, 23.42667], "uv_size": [-6.384, -2.08534]},
								"west": {"uv": [6.384, 23.42667], "uv_size": [-6.384, -2.08534]},
								"up": {"uv": [0, 21.34133], "uv_size": [6.384, 2.08534]},
								"down": {"uv": [0, 21.34133], "uv_size": [6.384, 2.08534]}
							}
						},
						{
							"origin": [-4.09, 1.24, -2.30375],
							"size": [4.3175, 0.5225, 4.58375],
							"pivot": [-1.78125, 1.50125, -0.01187],
							"rotation": [0, 0, 10],
							"uv": {
								"north": {"uv": [2.544, 25.13333], "uv_size": [-2.544, -3.792]},
								"east": {"uv": [4.67733, 25.13333], "uv_size": [-4.67733, -3.792]},
								"south": {"uv": [6.384, 23.42667], "uv_size": [-6.384, -2.08534]},
								"west": {"uv": [6.81067, 25.13333], "uv_size": [-6.81067, -3.792]},
								"up": {"uv": [0, 21.34133], "uv_size": [2.544, 3.792]},
								"down": {"uv": [0, 21.34133], "uv_size": [2.544, 3.792]}
							}
						},
						{
							"origin": [-4.09, 1.335, -2.20875],
							"size": [4.3175, 0.5225, 4.39375],
							"pivot": [-1.78125, 1.59625, -0.01187],
							"rotation": [0, 0, -5],
							"uv": {
								"north": {"uv": [2.544, 25.13333], "uv_size": [-2.544, -3.792]},
								"east": {"uv": [4.67733, 25.13333], "uv_size": [-4.67733, -3.792]},
								"south": {"uv": [6.384, 23.42667], "uv_size": [-6.384, -2.08534]},
								"west": {"uv": [6.81067, 25.13333], "uv_size": [-6.81067, -3.792]},
								"up": {"uv": [0, 21.34133], "uv_size": [2.544, 3.792]},
								"down": {"uv": [0, 21.34133], "uv_size": [2.544, 3.792]}
							}
						},
						{
							"origin": [-4.09, 0.385, -2.20875],
							"size": [4.2175, 0.5225, 4.39375],
							"pivot": [-1.78125, 0.64625, -0.01187],
							"rotation": [0, 0, -5],
							"uv": {
								"north": {"uv": [2.544, 25.13333], "uv_size": [-2.544, -3.792]},
								"east": {"uv": [4.67733, 25.13333], "uv_size": [-4.67733, -3.792]},
								"south": {"uv": [6.384, 23.42667], "uv_size": [-6.384, -2.08534]},
								"west": {"uv": [6.81067, 25.13333], "uv_size": [-6.81067, -3.792]},
								"up": {"uv": [0, 21.34133], "uv_size": [2.544, 3.792]},
								"down": {"uv": [0, 21.34133], "uv_size": [2.544, 3.792]}
							}
						}
					]
				}
			]
		}
	]
}